distilabel/__init__.py
distilabel/__main__.py
distilabel/constants.py
distilabel/distiset.py
distilabel/embeddings.py
distilabel/envs.py
distilabel/errors.py
distilabel/exceptions.py
distilabel/llms.py
distilabel/cli/__init__.py
distilabel/cli/app.py
distilabel/cli/pipeline/__init__.py
distilabel/cli/pipeline/app.py
distilabel/cli/pipeline/utils.py
distilabel/mixins/__init__.py
distilabel/mixins/requirements.py
distilabel/mixins/runtime_parameters.py
distilabel/mixins/signature.py
distilabel/models/__init__.py
distilabel/models/base_clients/__init__.py
distilabel/models/base_clients/inference_endpoints.py
distilabel/models/base_clients/openai.py
distilabel/models/embeddings/__init__.py
distilabel/models/embeddings/base.py
distilabel/models/embeddings/llamacpp.py
distilabel/models/embeddings/sentence_transformers.py
distilabel/models/embeddings/vllm.py
distilabel/models/image_generation/__init__.py
distilabel/models/image_generation/base.py
distilabel/models/image_generation/openai.py
distilabel/models/image_generation/utils.py
distilabel/models/image_generation/huggingface/__init__.py
distilabel/models/image_generation/huggingface/inference_endpoints.py
distilabel/models/llms/__init__.py
distilabel/models/llms/anthropic.py
distilabel/models/llms/anyscale.py
distilabel/models/llms/azure.py
distilabel/models/llms/base.py
distilabel/models/llms/cohere.py
distilabel/models/llms/groq.py
distilabel/models/llms/litellm.py
distilabel/models/llms/llamacpp.py
distilabel/models/llms/mistral.py
distilabel/models/llms/mlx.py
distilabel/models/llms/moa.py
distilabel/models/llms/ollama.py
distilabel/models/llms/openai.py
distilabel/models/llms/together.py
distilabel/models/llms/utils.py
distilabel/models/llms/vertexai.py
distilabel/models/llms/vllm.py
distilabel/models/llms/huggingface/__init__.py
distilabel/models/llms/huggingface/inference_endpoints.py
distilabel/models/llms/huggingface/transformers.py
distilabel/models/mixins/__init__.py
distilabel-1.5.2.dist-info/METADATA
distilabel-1.5.2.dist-info/WHEEL
distilabel-1.5.2.dist-info/entry_points.txt
distilabel-1.5.2.dist-info/licenses/LICENSE
distilabel-1.5.2.dist-info/licenses/LICENSE_HEADER
distilabel-1.5.2.dist-info/RECORD
