Metadata-Version: 2.4
Name: distilabel
Version: 1.5.2
Summary: Distilabel is an AI Feedback (AIF) framework for building datasets with and for LLMs.
Project-URL: Documentation, https://distilabel.argilla.io/
Project-URL: Issues, https://github.com/argilla/distilabel/issues
Project-URL: Source, https://github.com/argilla/distilabel
Author-email: Argilla <admin@argilla.io>
License-Expression: Apache-2.0
License-File: LICENSE
License-File: LICENSE_HEADER
Keywords: alignment,annotation,data,llm,rlaif,synthetic
Classifier: Development Status :: 4 - Beta
Classifier: Programming Language :: Python
Classifier: Programming Language :: Python :: 3.9
Classifier: Programming Language :: Python :: 3.10
Classifier: Programming Language :: Python :: 3.11
Classifier: Programming Language :: Python :: 3.12
Classifier: Programming Language :: Python :: Implementation :: CPython
Classifier: Programming Language :: Python :: Implementation :: PyPy
Requires-Python: >=3.9
Requires-Dist: datasets>=2.16.0
Requires-Dist: httpx>=0.25.2
Requires-Dist: importlib-resources>=6.1.1; python_version < '3.9'
Requires-Dist: jinja2>=3.1.2
Requires-Dist: multiprocess>=0.70
Requires-Dist: nest-asyncio>=1.6.0
Requires-Dist: networkx>=3.0
Requires-Dist: orjson>=3.10.0
Requires-Dist: portalocker>=2.8.2
Requires-Dist: pydantic>=2.0
Requires-Dist: rich>=13.5.0
Requires-Dist: scipy>=1.10.0
Requires-Dist: setuptools
Requires-Dist: tblib>=3.0.0
Requires-Dist: typer>=0.9.0
Requires-Dist: universal-pathlib>=0.2.2
Provides-Extra: anthropic
Requires-Dist: anthropic>=0.20.0; extra == 'anthropic'
Provides-Extra: argilla
Requires-Dist: argilla>=2.0.0; extra == 'argilla'
Requires-Dist: ipython; extra == 'argilla'
Provides-Extra: cohere
Requires-Dist: cohere>=5.2.0; extra == 'cohere'
Provides-Extra: dev
Requires-Dist: pre-commit>=3.5.0; extra == 'dev'
Requires-Dist: ruff==0.8.1; extra == 'dev'
Provides-Extra: docs
Requires-Dist: cairosvg>=2.7.1; extra == 'docs'
Requires-Dist: material-plausible-plugin>=0.2.0; extra == 'docs'
Requires-Dist: mike>=2.0.0; extra == 'docs'
Requires-Dist: mkdocs-gen-files>=0.5.0; extra == 'docs'
Requires-Dist: mkdocs-glightbox>=0.4.0; extra == 'docs'
Requires-Dist: mkdocs-literate-nav>=0.6.1; extra == 'docs'
Requires-Dist: mkdocs-material>=9.5.17; extra == 'docs'
Requires-Dist: mkdocs-section-index>=0.3.8; extra == 'docs'
Requires-Dist: mkdocstrings[python]>=0.24.0; extra == 'docs'
Requires-Dist: mknotebooks>=0.8.0; extra == 'docs'
Requires-Dist: pandas>=2.0; extra == 'docs'
Requires-Dist: pillow>=9.5.0; extra == 'docs'
Requires-Dist: tabulate>=0.9.0; extra == 'docs'
Provides-Extra: faiss-cpu
Requires-Dist: faiss-cpu>=1.8.0; extra == 'faiss-cpu'
Provides-Extra: faiss-gpu
Requires-Dist: faiss-gpu>=1.7.2; extra == 'faiss-gpu'
Provides-Extra: groq
Requires-Dist: groq>=0.4.1; extra == 'groq'
Provides-Extra: hf-inference-endpoints
Requires-Dist: huggingface-hub>=0.22.0; extra == 'hf-inference-endpoints'
Provides-Extra: hf-transformers
Requires-Dist: torch>=2.0.0; extra == 'hf-transformers'
Requires-Dist: transformers>=4.34.1; extra == 'hf-transformers'
Provides-Extra: instructor
Requires-Dist: instructor>=1.2.3; extra == 'instructor'
Provides-Extra: litellm
Requires-Dist: litellm>=1.30.0; extra == 'litellm'
Provides-Extra: llama-cpp
Requires-Dist: llama-cpp-python>=0.2.0; extra == 'llama-cpp'
Provides-Extra: minhash
Requires-Dist: datasketch>=1.6.5; extra == 'minhash'
Requires-Dist: nltk>3.8.1; extra == 'minhash'
Provides-Extra: mistralai
Requires-Dist: mistralai>=1.0.0; extra == 'mistralai'
Provides-Extra: mlx
Requires-Dist: mlx-lm<0.22.0,>=0.21.0; extra == 'mlx'
Requires-Dist: mlx>=0.21.0; extra == 'mlx'
Provides-Extra: ollama
Requires-Dist: ollama>=0.1.7; extra == 'ollama'
Provides-Extra: openai
Requires-Dist: openai>=1.0.0; extra == 'openai'
Provides-Extra: outlines
Requires-Dist: numba>=0.54.0; extra == 'outlines'
Requires-Dist: outlines>=0.0.40; extra == 'outlines'
Provides-Extra: ray
Requires-Dist: ray[default]>=2.31.0; extra == 'ray'
Provides-Extra: sentence-transformers
Requires-Dist: sentence-transformers>=3.0.0; extra == 'sentence-transformers'
Provides-Extra: tests
Requires-Dist: nest-asyncio; extra == 'tests'
Requires-Dist: pytest-asyncio; extra == 'tests'
Requires-Dist: pytest-codspeed; extra == 'tests'
Requires-Dist: pytest-timeout; extra == 'tests'
Requires-Dist: pytest>=7.4.0; extra == 'tests'
Provides-Extra: text-clustering
Requires-Dist: matplotlib>=3.8.3; extra == 'text-clustering'
Requires-Dist: scikit-learn>=1.4.1; extra == 'text-clustering'
Requires-Dist: umap-learn>=0.5.6; extra == 'text-clustering'
Provides-Extra: vertexai
Requires-Dist: google-cloud-aiplatform>=1.38.0; extra == 'vertexai'
Provides-Extra: vision
Requires-Dist: pillow>=10.3.0; extra == 'vision'
Provides-Extra: vllm
Requires-Dist: filelock>=3.13.4; extra == 'vllm'
Requires-Dist: vllm>=0.5.3; extra == 'vllm'
